tiled/__init__.py
tiled/__main__.py
tiled/_version.py
tiled/alembic_utils.py
tiled/authenticators.py
tiled/config.py
tiled/iterviews.py
tiled/links.py
tiled/media_type_registration.py
tiled/mimetypes.py
tiled/ndslice.py
tiled/profiles.py
tiled/queries.py
tiled/query_registration.py
tiled/schemas.py
tiled/storage.py
tiled/stream_messages.py
tiled/type_aliases.py
tiled/utils.py
tiled/validation_registration.py
tiled/_tests/__init__.py
tiled/_tests/conftest.py
tiled/_tests/test_access_control.py
tiled/_tests/test_access_policy.py
tiled/_tests/test_allow_origins.py
tiled/_tests/test_array.py
tiled/_tests/test_asset_access.py
tiled/_tests/test_authentication.py
tiled/_tests/test_authenticators.py
tiled/_tests/test_awkward.py
tiled/_tests/test_caches.py
tiled/_tests/test_catalog.py
tiled/_tests/test_cli.py
tiled/_tests/test_client.py
tiled/_tests/test_client_cache.py
tiled/_tests/test_client_smoke.py
tiled/_tests/test_composite.py
tiled/_tests/test_compression.py
tiled/_tests/test_config.py
tiled/_tests/test_connection_pool.py
tiled/_tests/test_container_fields.py
tiled/_tests/test_container_files.py
tiled/_tests/test_csv_adapter.py
tiled/_tests/test_custom_format.py
tiled/_tests/test_dataframe.py
tiled/_tests/test_decoders.py
tiled/_tests/test_device_flow.py
tiled/_tests/test_directory_walker.py
tiled/_tests/test_distinct.py
tiled/_tests/test_entrypoint_string.py
tiled/_tests/test_export.py
tiled/_tests/test_hdf5.py
tiled/_tests/test_history.py
tiled/_tests/test_import_object.py
tiled/_tests/test_in_memory_authn.py
tiled/_tests/test_indexers.py
tiled/_tests/test_inlined_contents.py
tiled/_tests/test_jpeg.py
tiled/_tests/test_json.py
tiled/_tests/test_metrics.py
tiled/_tests/test_mount_node.py
tiled/_tests/test_no_heavy_imports.py
tiled/_tests/test_npy.py
tiled/_tests/test_openapi.py
tiled/_tests/test_pagination.py
tiled/_tests/test_pickle.py
tiled/_tests/test_profiles.py
tiled/_tests/test_protocols.py
tiled/_tests/test_queries.py
tiled/_tests/test_register.py
tiled-0.2.3.dist-info/METADATA
tiled-0.2.3.dist-info/WHEEL
tiled-0.2.3.dist-info/entry_points.txt
tiled-0.2.3.dist-info/licenses/LICENSE
tiled-0.2.3.dist-info/RECORD
